Workbook

Sheet Executive Summary
A1: SREE BALAJI GOLD (SBG) COMMERCIAL SUITE
A2: Manual Verification Matrix & Quality Assurance Plan • Version 2.0
A4: TEST EXECUTION GUIDELINES
A5: 1. This workbook contains the definitive manual testing checklist for the current SBG application.
A6: 2. Switch to the 'Manual Test Matrix' tab to execute step-by-step test cases across all 18 functional modules.
A7: 3. Select Status ('PASS', 'FAIL', or 'PENDING') from the dropdown list in Column I.
A8: 4. Conditional formatting automatically highlights PASSED cases in green and FAILED cases in red.
A9: 5. Record any behavioral deviations or bugs in Column J ('Tester Notes / Observation').
A11: TEST MODULE SUMMARY & COVERAGE
A13: Module ID | B13: Module Name | C13: Total Cases | D13: Passed | E13: Failed | F13: Pending | G13: % Passed
A14: MOD-01 | B14: Authentication & Session Management | C14: 6 | D14: =COUNTIFS('Manual Test Matrix'!$B:$B, "MOD-01", 'Manual Test Matrix'!$I:$I, "PASS") | E14: =COUNTIFS('Manual Test Matrix'!$B:$B, "MOD-01", 'Manual Test Matrix'!$I:$I, "FAIL") | F14: =COUNTIFS('Manual Test Matrix'!$B:$B, "MOD-01", 'Manual Test Matrix'!$I:$I, "PENDING") | G14: =IF(C14>0, D14/C14, 0)
A15: MOD-02 | B15: Header, Navigation & Live Gold Rate Engine | C15: 7 | D15: =COUNTIFS('Manual Test Matrix'!$B:$B, "MOD-02", 'Manual Test Matrix'!$I:$I, "PASS") | E15: =COUNTIFS('Manual Test Matrix'!$B:$B, "MOD-02", 'Manual Test Matrix'!$I:$I, "FAIL") | F15: =COUNTIFS('Manual Test Matrix'!$B:$B, "MOD-02", 'Manual Test Matrix'!$I:$I, "PENDING") | G15: =IF(C15>0, D15/C15, 0)
A16: MOD-03 | B16: Commercial Dashboard & KPI Metrics | C16: 6 | D16: =COUNTIFS('Manual Test Matrix'!$B:$B, "MOD-03", 'Manual Test Matrix'!$I:$I, "PASS") | E16: =COUNTIFS('Manual Test Matrix'!$B:$B, "MOD-03", 'Manual Test Matrix'!$I:$I, "FAIL") | F16: =COUNTIFS('Manual Test Matrix'!$B:$B, "MOD-03", 'Manual Test Matrix'!$I:$I, "PENDING") | G16: =IF(C16>0, D16/C16, 0)
A17: MOD-04 | B17: Customer KYC Directory & Master Data | C17: 7 | D17: =COUNTIFS('Manual Test Matrix'!$B:$B, "MOD-04", 'Manual Test Matrix'!$I:$I, "PASS") | E17: =COUNTIFS('Manual Test Matrix'!$B:$B, "MOD-04", 'Manual Test Matrix'!$I:$I, "FAIL") | F17: =COUNTIFS('Manual Test Matrix'!$B:$B, "MOD-04", 'Manual Test Matrix'!$I:$I, "PENDING") | G17: =IF(C17>0, D17/C17, 0)
A18: MOD-05 | B18: Customer Profile, Dual-Ledger & Sheet Import | C18: 8 | D18: =COUNTIFS('Manual Test Matrix'!$B:$B, "MOD-05", 'Manual Test Matrix'!$I:$I, "PASS") | E18: =COUNTIFS('Manual Test Matrix'!$B:$B, "MOD-05", 'Manual Test Matrix'!$I:$I, "FAIL") | F18: =COUNTIFS('Manual Test Matrix'!$B:$B, "MOD-05", 'Manual Test Matrix'!$I:$I, "PENDING") | G18: =IF(C18>0, D18/C18, 0)
A19: MOD-06 | B19: Commercial Orders & Production Tracking | C19: 6 | D19: =COUNTIFS('Manual Test Matrix'!$B:$B, "MOD-06", 'Manual Test Matrix'!$I:$I, "PASS") | E19: =COUNTIFS('Manual Test Matrix'!$B:$B, "MOD-06", 'Manual Test Matrix'!$I:$I, "FAIL") | F19: =COUNTIFS('Manual Test Matrix'!$B:$B, "MOD-06", 'Manual Test Matrix'!$I:$I, "PENDING") | G19: =IF(C19>0, D19/C19, 0)
A20: MOD-07 | B20: Dual-Ledger Transaction Management | C20: 7 | D20: =COUNTIFS('Manual Test Matrix'!$B:$B, "MOD-07", 'Manual Test Matrix'!$I:$I, "PASS") | E20: =COUNTIFS('Manual Test Matrix'!$B:$B, "MOD-07", 'Manual Test Matrix'!$I:$I, "FAIL") | F20: =COUNTIFS('Manual Test Matrix'!$B:$B, "MOD-07", 'Manual Test Matrix'!$I:$I, "PENDING") | G20: =IF(C20>0, D20/C20, 0)
A21: MOD-08 | B21: Quick Payment & Receipt Voucher Modal | C21: 6 | D21: =COUNTIFS('Manual Test Matrix'!$B:$B, "MOD-08", 'Manual Test Matrix'!$I:$I, "PASS") | E21: =COUNTIFS('Manual Test Matrix'!$B:$B, "MOD-08", 'Manual Test Matrix'!$I:$I, "FAIL") | F21: =COUNTIFS('Manual Test Matrix'!$B:$B, "MOD-08", 'Manual Test Matrix'!$I:$I, "PENDING") | G21: =IF(C21>0, D21/C21, 0)
A22: MOD-09 | B22: Estimate Cost Sheet Calculation Engine | C22: 8 | D22: =COUNTIFS('Manual Test Matrix'!$B:$B, "MOD-09", 'Manual Test Matrix'!$I:$I, "PASS") | E22: =COUNTIFS('Manual Test Matrix'!$B:$B, "MOD-09", 'Manual Test Matrix'!$I:$I, "FAIL") | F22: =COUNTIFS('Manual Test Matrix'!$B:$B, "MOD-09", 'Manual Test Matrix'!$I:$I, "PENDING") | G22: =IF(C22>0, D22/C22, 0)
A23: MOD-10 | B23: Estimate Settlement Presets Engine | C23: 7 | D23: =COUNTIFS('Manual Test Matrix'!$B:$B, "MOD-10", 'Manual Test Matrix'!$I:$I, "PASS") | E23: =COUNTIFS('Manual Test Matrix'!$B:$B, "MOD-10", 'Manual Test Matrix'!$I:$I, "FAIL") | F23: =COUNTIFS('Manual Test Matrix'!$B:$B, "MOD-10", 'Manual Test Matrix'!$I:$I, "PENDING") | G23: =IF(C23>0, D23/C23, 0)
A24: MOD-11 | B24: Estimate Lifecycle & Atomic Financial Postings | C24: 6 | D24: =COUNTIFS('Manual Test Matrix'!$B:$B, "MOD-11", 'Manual Test Matrix'!$I:$I, "PASS") | E24: =COUNTIFS('Manual Test Matrix'!$B:$B, "MOD-11", 'Manual Test Matrix'!$I:$I, "FAIL") | F24: =COUNTIFS('Manual Test Matrix'!$B:$B, "MOD-11", 'Manual Test Matrix'!$I:$I, "PENDING") | G24: =IF(C24>0, D24/C24, 0)
A25: MOD-12 | B25: Estimate Invoice Details & Print Output | C25: 8 | D25: =COUNTIFS('Manual Test Matrix'!$B:$B, "MOD-12", 'Manual Test Matrix'!$I:$I, "PASS") | E25: =COUNTIFS('Manual Test Matrix'!$B:$B, "MOD-12", 'Manual Test Matrix'!$I:$I, "FAIL") | F25: =COUNTIFS('Manual Test Matrix'!$B:$B, "MOD-12", 'Manual Test Matrix'!$I:$I, "PENDING") | G25: =IF(C25>0, D25/C25, 0)
A26: MOD-13 | B26: Gold & Cash Spot Rate Settlements | C26: 6 | D26: =COUNTIFS('Manual Test Matrix'!$B:$B, "MOD-13", 'Manual Test Matrix'!$I:$I, "PASS") | E26: =COUNTIFS('Manual Test Matrix'!$B:$B, "MOD-13", 'Manual Test Matrix'!$I:$I, "FAIL") | F26: =COUNTIFS('Manual Test Matrix'!$B:$B, "MOD-13", 'Manual Test Matrix'!$I:$I, "PENDING") | G26: =IF(C26>0, D26/C26, 0)
A27: MOD-14 | B27: Commercial Reports & CSV Export Registers | C27: 6 | D27: =COUNTIFS('Manual Test Matrix'!$B:$B, "MOD-14", 'Manual Test Matrix'!$I:$I, "PASS") | E27: =COUNTIFS('Manual Test Matrix'!$B:$B, "MOD-14", 'Manual Test Matrix'!$I:$I, "FAIL") | F27: =COUNTIFS('Manual Test Matrix'!$B:$B, "MOD-14", 'Manual Test Matrix'!$I:$I, "PENDING") | G27: =IF(C27>0, D27/C27, 0)
A28: MOD-15 | B28: Immutable Audit Trail & Data Integrity | C28: 5 | D28: =COUNTIFS('Manual Test Matrix'!$B:$B, "MOD-15", 'Manual Test Matrix'!$I:$I, "PASS") | E28: =COUNTIFS('Manual Test Matrix'!$B:$B, "MOD-15", 'Manual Test Matrix'!$I:$I, "FAIL") | F28: =COUNTIFS('Manual Test Matrix'!$B:$B, "MOD-15", 'Manual Test Matrix'!$I:$I, "PENDING") | G28: =IF(C28>0, D28/C28, 0)
A29: MOD-16 | B29: Users, Roles & Access Control | C29: 6 | D29: =COUNTIFS('Manual Test Matrix'!$B:$B, "MOD-16", 'Manual Test Matrix'!$I:$I, "PASS") | E29: =COUNTIFS('Manual Test Matrix'!$B:$B, "MOD-16", 'Manual Test Matrix'!$I:$I, "FAIL") | F29: =COUNTIFS('Manual Test Matrix'!$B:$B, "MOD-16", 'Manual Test Matrix'!$I:$I, "PENDING") | G29: =IF(C29>0, D29/C29, 0)
A30: MOD-17 | B30: Settings, Company GSTIN & Bank Details | C30: 6 | D30: =COUNTIFS('Manual Test Matrix'!$B:$B, "MOD-17", 'Manual Test Matrix'!$I:$I, "PASS") | E30: =COUNTIFS('Manual Test Matrix'!$B:$B, "MOD-17", 'Manual Test Matrix'!$I:$I, "FAIL") | F30: =COUNTIFS('Manual Test Matrix'!$B:$B, "MOD-17", 'Manual Test Matrix'!$I:$I, "PENDING") | G30: =IF(C30>0, D30/C30, 0)
A31: MOD-18 | B31: Edge Cases, Precision & Boundary Conditions | C31: 7 | D31: =COUNTIFS('Manual Test Matrix'!$B:$B, "MOD-18", 'Manual Test Matrix'!$I:$I, "PASS") | E31: =COUNTIFS('Manual Test Matrix'!$B:$B, "MOD-18", 'Manual Test Matrix'!$I:$I, "FAIL") | F31: =COUNTIFS('Manual Test Matrix'!$B:$B, "MOD-18", 'Manual Test Matrix'!$I:$I, "PENDING") | G31: =IF(C31>0, D31/C31, 0)
A32: TOTAL | B32: All 18 Modules Combined | C32: =SUM(C14:C31) | D32: =SUM(D14:D31) | E32: =SUM(E14:E31) | F32: =SUM(F14:F31) | G32: =IF(C32>0, D32/C32, 0)

Sheet Manual Test Matrix
A1: Test ID | B1: Module ID | C1: Module Name | D1: Test Scenario / Feature | E1: Prerequisites | F1: Step-by-Step Test Actions | G1: Test Data | H1: Expected Result | I1: Status | J1: Tester Notes / Observation
A2: TC-AUTH-01 | B2: MOD-01 | C2: Authentication & Session Management | D2: Successful Admin Login | E2: Logged out state | F2: 1. Navigate to base URL. 2. Enter admin username and password. 3. Click "Sign In". | G2: Username: sreebalajigold@gmail.com Password: password | H2: User is authenticated and redirected to Dashboard. Current user badge shows "ADMIN". | I2: PENDING
A3: TC-AUTH-02 | B3: MOD-01 | C3: Authentication & Session Management | D3: Invalid Password Rejection | E3: Logged out state | F3: 1. Enter valid username with wrong password. 2. Click "Sign In". | G3: Username: sreebalajigold@gmail.com Password: wrongpass | H3: Error message displayed: "Invalid username or password. Please verify your credentials." Login fails. | I3: PENDING
A4: TC-AUTH-03 | B4: MOD-01 | C4: Authentication & Session Management | D4: Password Visibility Toggle | E4: Logged out state | F4: 1. Type password in password field. 2. Click the eye icon button. | G4: Password: secretpassword | H4: Password input changes from masked (••••••) to clear text and back upon toggle. | I4: PENDING
A5: TC-AUTH-04 | B5: MOD-01 | C5: Authentication & Session Management | D5: Password Reset Modal Workflow | E5: Logged out state | F5: 1. Click "Forgot your password?". 2. Enter registered email. 3. Enter new password and confirmation. 4. Submit. | G5: Email: sreebalajigold@gmail.com New Pass: newpass123 Confirm: newpass123 | H5: Success banner displays, modal closes, user can immediately login with the new password. | I5: PENDING
A6: TC-AUTH-05 | B6: MOD-01 | C6: Authentication & Session Management | D6: Session Persistence on Page Reload | E6: User logged in | F6: 1. Log in successfully. 2. Press browser Refresh (F5 / Cmd+R). | G6: N/A | H6: User remains logged in on the active tab without being kicked back to login screen. | I6: PENDING
A7: TC-AUTH-06 | B7: MOD-01 | C7: Authentication & Session Management | D7: Secure User Logout | E7: User logged in | F7: 1. Click user avatar on top-right. 2. Click "Sign Out". | G7: N/A | H7: Session clears from localStorage (sbgauth). User is immediately redirected to Login view. | I7: PENDING
A8: TC-NAV-01 | B8: MOD-02 | C8: Header, Navigation & Live Gold Rate Engine | D8: Desktop Sidebar Navigation | E8: Admin user | F8: 1. Click each sidebar item: Dashboard, Customers, SBG Estimates, Audit & Security, Users & Access, Settings. | G8: N/A | H8: View updates smoothly with URL parameter ?tab=... and correct page content rendered. | I8: PENDING
A9: TC-NAV-02 | B9: MOD-02 | C9: Header, Navigation & Live Gold Rate Engine | D9: Sidebar Collapse & Expand Toggle | E9: Desktop viewport | F9: 1. Click the collapse arrow icon next to sidebar. 2. Verify collapsed icon-only state. 3. Click expand icon. | G9: N/A | H9: Sidebar collapses smoothly, main content expands; state persists across page reload (sbgsidebarcollapsed). | I9: PENDING
A10: TC-NAV-03 | B10: MOD-02 | C10: Header, Navigation & Live Gold Rate Engine | D10: Role-Based Navigation Filtering | E10: Staff / Client login | F10: 1. Log in as STAFF user. 2. Check sidebar items. 3. Log in as CLIENT user. | G10: Staff user Client user | H10: Staff sees Dashboard, Customers, Estimates, Settings. Client sees only Dashboard, Customers, Estimates. | I10: PENDING
A11: TC-NAV-04 | B11: MOD-02 | C11: Header, Navigation & Live Gold Rate Engine | D11: Live Gold Rate Ticker Display | E11: Dashboard open | F11: 1. Observe gold rate pill in header. 2. Check purity dropdown (24KT, 22KT, 18KT, 14KT, 99.5%). | G11: Purity options | H11: Displayed rate adjusts according to formula: $\text{Rate} = \text{Base Rate} \times \left(\frac{\text{Purity}}{100}\right)$. Live indicator pulses green. | I11: PENDING
A12: TC-NAV-05 | B12: MOD-02 | C12: Header, Navigation & Live Gold Rate Engine | D12: Live Rate Manual Refresh | E12: Dashboard open | F12: 1. Click the Sparkles/Refresh icon on rate badge in header. | G12: N/A | H12: Trigger fetches live spot price from online API or applies latest ticker rate; timestamp updates. | I12: PENDING
A13: TC-NAV-06 | B13: MOD-02 | C13: Header, Navigation & Live Gold Rate Engine | D13: Manual Market Gold Rate Override | E13: Settings or Rate Modal | F13: 1. Click rate pill to open edit modal. 2. Enter new rate value (e.g. ₹ 7,500.00/g). 3. Click Save. | G13: Rate: 7500.00 | H13: Market rate updates across all headers, estimate builders, and valuation widgets immediately. | I13: PENDING
... A119: TC-EDGE-07 | B119: MOD-18 | C119: Edge Cases, Precision & Boundary Conditions | D119: Special Characters in ERP References & Remarks | E119: New transaction / Estimate | F119: 1. Enter reference with slashes, dashes, and hashes (e.g. RD/BB#094/26-27 & CO.). 2. Save and view in print. | G119: Reference: RD/BB#094/26-27 & CO. | H119: String renders cleanly without escaping bugs or layout breaks in table or invoice. | I119: PENDING
